src/SNN_core/synapse_core/apply_reward.sv
module apply_reward #(
    parameter int LR_SHIFT = 2,
    parameter int LEARNING_MODE = 2
  ) (
    input  logic signed [3:0] dopamine,
    input  logic signed [8:0] elig_trace,
    input  logic              reward_en,
    output logic signed [8:0] delta_w
  );

  if (LEARNING_MODE == 1) begin : g_rstdp
    logic signed [12:0] product;
    always_comb begin
      product = '0;
      delta_w = '0;
      if (reward_en) begin
        product = (elig_trace * dopamine) >>> LR_SHIFT;
        if      (product > 255)  delta_w =  255;
        else if (product < -255) delta_w = -255;
        else                     delta_w = product[8:0];
      end
    end
  end else if (LEARNING_MODE == 2) begin : g_stdp
    logic signed [12:0] product;
    always_comb begin
      product = elig_trace >>> LR_SHIFT;
      delta_w = product[8:0];
    end
  end else begin : g_off
    assign delta_w = '0;
  end

endmodule

src/SNN_core/synapse_core/tb_apply_reward.sv
`timescale 1ns / 1ps
//////////////////////////////////////////////////////////////////////////////////
// Company:
// Engineer:
//
// Create Date: 04/13/2026
// Design Name:
// Module Name: tb_apply_reward
// Project Name:
// Target Devices:
// Tool Versions:
// Description: Testbench for apply_reward -- covers all three learning modes
//              (None / R-STDP / STDP), reward_en gating, sign handling, and
//              boundary values.
//
//              NOTE: apply_reward is purely combinational. rst and clk are
//              kept as ports for interface consistency but have no effect on
//              delta_w. Gating is via reward_en only.
//
// Dependencies: apply_reward.sv
//
// Revision:
// Revision 0.02 - Updated for combinational apply_reward (removed registered
//                 TEST 0 / TEST 10 hold assumptions)
//
//////////////////////////////////////////////////////////////////////////////////

module tb_apply_reward ();

    // --------------------------------------------------------------------------
    // Parameters
    // --------------------------------------------------------------------------
    localparam int LR_SHIFT = 2;  // Must match DUT default

    // --------------------------------------------------------------------------
    // Shared DUT signals
    // --------------------------------------------------------------------------
    logic              clk;
    logic signed [3:0] dopamine;
    logic signed [8:0] elig_trace;
    logic              reward_en;
    logic              rst;

    // Output per learning-mode instance
    logic signed [8:0] delta_w_none;   // LEARNING_MODE = 0
    logic signed [8:0] delta_w_rstdp;  // LEARNING_MODE = 1
    logic signed [8:0] delta_w_stdp;   // LEARNING_MODE = 2

    // --------------------------------------------------------------------------
    // DUT instantiation -- one per learning mode
    // --------------------------------------------------------------------------
    apply_reward #(.LR_SHIFT(LR_SHIFT), .LEARNING_MODE(0)) dut_none (
        .dopamine   (dopamine),
        .elig_trace (elig_trace),
        .reward_en  (reward_en),
        .delta_w    (delta_w_none)
    );

    apply_reward #(.LR_SHIFT(LR_SHIFT), .LEARNING_MODE(1)) dut_rstdp (
        .dopamine   (dopamine),
        .elig_trace (elig_trace),
        .reward_en  (reward_en),
        .delta_w    (delta_w_rstdp)
    );

    apply_reward #(.LR_SHIFT(LR_SHIFT), .LEARNING_MODE(2)) dut_stdp (
        .dopamine   (dopamine),
        .elig_trace (elig_trace),
        .reward_en  (reward_en),
        .delta_w    (delta_w_stdp)
    );

    // --------------------------------------------------------------------------
    // Clock generation -- 10 ns period (100 MHz)
    // --------------------------------------------------------------------------
    initial clk = 1'b0;
    always #5 clk = ~clk;

    // --------------------------------------------------------------------------
    // Pass / fail counters
    // --------------------------------------------------------------------------
    int pass_count = 0;
    int fail_count = 0;

    // --------------------------------------------------------------------------
    // Helper task: drive inputs for one clock cycle
    // --------------------------------------------------------------------------
    task automatic apply_inputs(
        input logic signed [3:0] dop_val,
        input logic signed [8:0] elig_val,
        input logic              en_val
    );
        @(negedge clk);
        dopamine   = dop_val;
        elig_trace = elig_val;
        reward_en  = en_val;
        @(posedge clk);
        #1;  // let outputs settle
    endtask

    // --------------------------------------------------------------------------
    // Helper task: idle (zero input, reward disabled) for N cycles
    // --------------------------------------------------------------------------
    task automatic idle_cycles(input int n);
        repeat (n) apply_inputs(4'sd0, 9'sd0, 1'b0);
    endtask

    // --------------------------------------------------------------------------
    // Assertion helper: check one output value, print PASS / FAIL
    // --------------------------------------------------------------------------
    task automatic check(
        input string             label,
        input logic signed [8:0] got,
        input logic signed [8:0] expected
    );
        if (got === expected) begin
            $display("  PASS  %s : delta_w = %0d", label, got);
            pass_count++;
        end else begin
            $display("  FAIL  %s : got %0d, expected %0d", label, got, expected);
            fail_count++;
        end
    endtask

    // --------------------------------------------------------------------------
    // Continuous monitor: show all outputs on every posedge
    // --------------------------------------------------------------------------
    always @(posedge clk) begin
        #1;
        $display("[%0t ns]  dop=%0d  elig=%0d  en=%b | none=%0d  rstdp=%0d  stdp=%0d",
                 $time, dopamine, elig_trace, reward_en,
                 delta_w_none, delta_w_rstdp, delta_w_stdp);
    end

    // --------------------------------------------------------------------------
    // Stimulus
    // --------------------------------------------------------------------------
    initial begin
        // ----- Initialise -----
        dopamine   = 4'sd0;
        elig_trace = 9'sd0;
        reward_en  = 1'b0;
        rst        = 1'b1;

        idle_cycles(2);
        @(negedge clk);
        rst = 1'b0;

        // ==================================================================
        // TEST 0: reward_en=0 -- delta_w must be zero regardless of inputs
        //
        // apply_reward is combinational: rst has no effect on delta_w.
        // Gating is purely through reward_en.
        // ==================================================================
        $display("\n[%0t] TEST 0: reward_en disabled -- output must be zero", $time);
        apply_inputs(4'sd5, 9'sd200, 1'b0);
        check("none  | en=0, elig=200, dop=5", delta_w_none,  8'sd0);
        check("rstdp | en=0, elig=200, dop=5", delta_w_rstdp, 8'sd0);
        check("stdp  | en=0, elig=200, dop=5", delta_w_stdp,  8'sd0);
        idle_cycles(1);

        // ==================================================================
        // TEST 1: reward_en=1 then reward_en=0 -- output returns to zero
        //
        // Combinational: delta_w tracks reward_en with no memory.
        // en=0 always produces 0, regardless of prior state.
        // ==================================================================
        $display("\n[%0t] TEST 1: reward_en gating -- en=0 gives zero, not hold", $time);
        apply_inputs(4'sd0, 9'sd100, 1'b1);   // en=1 → stdp delta_w=25
        check("stdp  | en=1, elig=100 : delta_w=25", delta_w_stdp, 8'sd25);
        apply_inputs(4'sd0, 9'sd200, 1'b0);   // en=0 → delta_w returns to 0
        check("stdp  | en=0, elig=200 : delta_w=0 (no hold)", delta_w_stdp, 8'sd0);
        idle_cycles(1);

        // ==================================================================
        // TEST 2: STDP mode -- positive eligibility trace
        //
        // delta_w = elig_trace >>> LR_SHIFT
        //   elig=100 -> 100 >>> 2 = 25
        //   elig=200 -> 200 >>> 2 = 50
        // ==================================================================
        $display("\n[%0t] TEST 2: STDP -- positive eligibility trace", $time);
        apply_inputs(4'sd0, 9'sd100, 1'b1);
        check("stdp  | elig=100, dop=0, en=1", delta_w_stdp,  8'sd25);

        apply_inputs(4'sd0, 9'sd200, 1'b1);
        check("stdp  | elig=200, dop=0, en=1", delta_w_stdp,  8'sd50);
        idle_cycles(1);

        // ==================================================================
        // TEST 3: STDP mode -- negative eligibility trace
        //
        // Arithmetic right shift must sign-extend:
        //   elig=-100 -> -100 >>> 2 = -25
        //   elig=-200 -> -200 >>> 2 = -50
        // ==================================================================
        $display("\n[%0t] TEST 3: STDP -- negative eligibility trace", $time);
        apply_inputs(4'sd0, -9'sd100, 1'b1);
        check("stdp  | elig=-100, dop=0, en=1", delta_w_stdp,  -8'sd25);

        apply_inputs(4'sd0, -9'sd200, 1'b1);
        check("stdp  | elig=-200, dop=0, en=1", delta_w_stdp,  -8'sd50);
        idle_cycles(1);

        // ==================================================================
        // TEST 4: STDP mode -- zero eligibility trace
        //
        // delta_w = 0 regardless of dopamine.
        // ==================================================================
        $display("\n[%0t] TEST 4: STDP -- zero eligibility trace", $time);
        apply_inputs(4'sd7, 9'sd0, 1'b1);
        check("stdp  | elig=0, dop=7, en=1", delta_w_stdp, 8'sd0);
        idle_cycles(1);

        // ==================================================================
        // TEST 5: R-STDP -- positive dopamine, positive trace
        //
        // delta_w = (elig_trace * dopamine) >>> LR_SHIFT
        //   elig=100, dop=3  -> 300  >>> 2 = 75
        //   elig=50,  dop=7  -> 350  >>> 2 = 87
        // ==================================================================
        $display("\n[%0t] TEST 5: R-STDP -- positive dopamine, positive trace", $time);
        apply_inputs(4'sd3, 9'sd100, 1'b1);
        check("rstdp | elig=100, dop=3,  en=1", delta_w_rstdp,  8'sd75);

        apply_inputs(4'sd7, 9'sd50, 1'b1);
        check("rstdp | elig=50,  dop=7,  en=1", delta_w_rstdp,  8'sd87);
        idle_cycles(1);

        // ==================================================================
        // TEST 6: R-STDP -- negative dopamine, positive trace
        //
        //   elig=100, dop=-3 -> -300 >>> 2 = -75
        //   elig=50,  dop=-7 -> -350 >>> 2 = -88  (floor of -87.5)
        // ==================================================================
        $display("\n[%0t] TEST 6: R-STDP -- negative dopamine, positive trace", $time);
        apply_inputs(-4'sd3, 9'sd100, 1'b1);
        check("rstdp | elig=100, dop=-3, en=1", delta_w_rstdp,  -8'sd75);

        apply_inputs(-4'sd7, 9'sd50, 1'b1);
        check("rstdp | elig=50,  dop=-7, en=1", delta_w_rstdp,  -8'sd88);
        idle_cycles(1);

        // ==================================================================
        // TEST 7: R-STDP -- positive dopamine, negative trace
        //
        //   elig=-100, dop=3 -> -300 >>> 2 = -75
        //   elig=-50,  dop=7 -> -350 >>> 2 = -88
        // ==================================================================
        $display("\n[%0t] TEST 7: R-STDP -- positive dopamine, negative trace", $time);
        apply_inputs(4'sd3, -9'sd100, 1'b1);
        check("rstdp | elig=-100, dop=3,  en=1", delta_w_rstdp, -8'sd75);

        apply_inputs(4'sd7, -9'sd50, 1'b1);
        check("rstdp | elig=-50,  dop=7,  en=1", delta_w_rstdp, -8'sd88);
        idle_cycles(1);

        // ==================================================================
        // TEST 8: R-STDP -- zero dopamine
        //
        // Product is zero regardless of elig_trace.
        // ==================================================================
        $display("\n[%0t] TEST 8: R-STDP -- zero dopamine", $time);
        apply_inputs(4'sd0, 9'sd255, 1'b1);
        check("rstdp | elig=255, dop=0, en=1", delta_w_rstdp, 8'sd0);
        idle_cycles(1);

        // ==================================================================
        // TEST 9: No-learning mode -- delta_w always zero
        //
        // Regardless of inputs the no-learning DUT must output zero.
        // ==================================================================
        $display("\n[%0t] TEST 9: No-learning mode -- delta_w must always be zero", $time);
        apply_inputs(4'sd7, 9'sd200, 1'b1);
        check("none  | elig=200, dop=7,  en=1", delta_w_none, 8'sd0);

        apply_inputs(-4'sd8, -9'sd255, 1'b1);
        check("none  | elig=-255, dop=-8, en=1", delta_w_none, 8'sd0);
        idle_cycles(1);

        // ==================================================================
        // TEST 10: Boundary -- maximum positive eligibility trace (STDP)
        //
        // elig=255 -> 255 >>> 2 = 63 (no overflow within 8-bit signed range)
        // ==================================================================
        $display("\n[%0t] TEST 10: STDP -- maximum positive elig_trace (255)", $time);
        apply_inputs(4'sd0, 9'sd255, 1'b1);
        check("stdp  | elig=255, dop=0, en=1", delta_w_stdp, 8'sd63);
        idle_cycles(1);

        // ==================================================================
        // TEST 11: Boundary -- maximum negative eligibility trace (STDP)
        //
        // elig=-256 -> -256 >>> 2 = -64
        // ==================================================================
        $display("\n[%0t] TEST 11: STDP -- maximum negative elig_trace (-256)", $time);
        apply_inputs(4'sd0, -9'sd256, 1'b1);
        check("stdp  | elig=-256, dop=0, en=1", delta_w_stdp, -8'sd64);
        idle_cycles(1);

        // ==================================================================
        // Summary
        // ==================================================================
        $display("\n[%0t] ===== Testbench complete: %0d passed, %0d failed =====",
                 $time, pass_count, fail_count);

        if (fail_count == 0)
            $display("[%0t] ALL TESTS PASSED", $time);
        else
            $display("[%0t] %0d TEST(S) FAILED -- see FAIL lines above", $time, fail_count);

        $finish;
    end

    // --------------------------------------------------------------------------
    // Waveform dump
    // --------------------------------------------------------------------------
    initial begin
        $dumpfile("tb_apply_reward.vcd");
        $dumpvars(0, tb_apply_reward);
    end

endmodule

src/SNN_core/synapse_core/tb_apply_reward.vcd
$date
	Sun Apr 26 20:48:19 2026
$end
$version
	Icarus Verilog
$end
$timescale
	1ps
$end
$scope module tb_apply_reward $end
$var wire 9 ! delta_w_stdp [8:0] $end
$var wire 9 " delta_w_rstdp [8:0] $end
$var wire 9 # delta_w_none [8:0] $end
$var parameter 32 $ LR_SHIFT $end
$var reg 1 % clk $end
$var reg 4 & dopamine [3:0] $end
$var reg 9 ' elig_trace [8:0] $end
$var reg 1 ( reward_en $end
$var reg 1 ) rst $end
$var integer 32 * fail_count [31:0] $end
$var integer 32 + pass_count [31:0] $end
$scope module dut_none $end
$var wire 4 , dopamine [3:0] $end
$var wire 9 - elig_trace [8:0] $end
$var wire 1 ( reward_en $end
$var parameter 32 . LEARNING_MODE $end
$var parameter 32 / LR_SHIFT $end
$var reg 9 0 delta_w [8:0] $end
$var reg 13 1 product [12:0] $end
$upscope $end
$scope module dut_rstdp $end
$var wire 4 2 dopamine [3:0] $end
$var wire 9 3 elig_trace [8:0] $end
$var wire 1 ( reward_en $end
$var parameter 32 4 LEARNING_MODE $end
$var parameter 32 5 LR_SHIFT $end
$var reg 9 6 delta_w [8:0] $end
$var reg 13 7 product [12:0] $end
$upscope $end
$scope module dut_stdp $end
$var wire 4 8 dopamine [3:0] $end
$var wire 9 9 elig_trace [8:0] $end
$var wire 1 ( reward_en $end
$var parameter 32 : LEARNING_MODE $end
$var parameter 32 ; LR_SHIFT $end
$var reg 9 < delta_w [8:0] $end
$var reg 13 = product [12:0] $end
$upscope $end
$scope task apply_inputs $end
$upscope $end
$scope task check $end
$upscope $end
$scope task idle_cycles $end
$upscope $end
$upscope $end
$enddefinitions $end
$comment Show the parameter values. $end
$dumpall
b10 ;
b10 :
b10 5
b1 4
b10 /
b0 .
b10 $
$end
#0
$dumpvars
b0 =
b0 <
b0 9
b0 8
b0 7
b0 6
b0 3
b0 2
b0 1
b0 0
b0 -
b0 ,
b0 +
b0 *
1)
0(
b0 '
b0 &
0%
b0 #
b0 "
b0 !
$end
#5000
1%
#10000
0%
#15000
1%
#20000
0%
#25000
1%
#30000
0)
0%
#35000
1%
#40000
b110010 !
b110010 <
b110010 =
b11001000 '
b11001000 -
b11001000 3
b11001000 9
b101 &
b101 ,
b101 2
b101 8
0%
#45000
1%
#46000
b1 *
b10 +
#50000
b0 =
b0 !
b0 <
b0 '
b0 -
b0 3
b0 9
b0 &
b0 ,
b0 2
b0 8
0%
#55000
1%
#60000
b11001 !
b11001 <
b11001 =
1(
b1100100 '
b1100100 -
b1100100 3
b1100100 9
0%
#65000
1%
#66000
b11 +
#70000
b110010 =
b110010 !
b110010 <
0(
b11001000 '
b11001000 -
b11001000 3
b11001000 9
0%
#75000
1%
#76000
b10 *
#80000
b0 =
b0 !
b0 <
b0 '
b0 -
b0 3
b0 9
0%
#85000
1%
#90000
b11001 !
b11001 <
b11001 =
1(
b1100100 '
b1100100 -
b1100100 3
b1100100 9
0%
#95000
1%
#96000
b100 +
#100000
b110010 =
b110010 !
b110010 <
b11001000 '
b11001000 -
b11001000 3
b11001000 9
0%
#105000
1%
#106000
b101 +
#110000
b0 =
b0 !
b0 <
0(
b0 '
b0 -
b0 3
b0 9
0%
#115000
1%
#120000
b111100111 !
b111100111 <
b1111111100111 =
1(
b110011100 '
b110011100 -
b110011100 3
b110011100 9
0%
#125000
1%
#126000
b110 +
#130000
b1111111001110 =
b111001110 !
b111001110 <
b100111000 '
b100111000 -
b100111000 3
b100111000 9
0%
#135000
1%
#136000
b111 +
#140000
b0 =
b0 !
b0 <
0(
b0 '
b0 -
b0 3
b0 9
0%
#145000
1%
#150000
1(
b111 &
b111 ,
b111 2
b111 8
0%
#155000
1%
#156000
b1000 +
#160000
0(
b0 &
b0 ,
b0 2
b0 8
0%
#165000
1%
#170000
b11001 !
b11001 <
b11001 =
b1001011 "
b1001011 6
b1001011 7
1(
b1100100 '
b1100100 -
b1100100 3
b1100100 9
b11 &
b11 ,
b11 2
b11 8
0%
#175000
1%
#176000
b1001 +
#180000
b1100 =
b1100 !
b1100 <
b1010111 7
b1010111 "
b1010111 6
b110010 '
b110010 -
b110010 3
b110010 9
b111 &
b111 ,
b111 2
b111 8
0%
#185000
1%
#186000
b1010 +
#190000
b0 =
b0 !
b0 <
b0 7
b0 "
b0 6
0(
b0 '
b0 -
b0 3
b0 9
b0 &
b0 ,
b0 2
b0 8
0%
#195000
1%
#200000
b11001 !
b11001 <
b11001 =
b110110101 "
b110110101 6
b1111110110101 7
1(
b1100100 '
b1100100 -
b1100100 3
b1100100 9
b1101 &
b1101 ,
b1101 2
b1101 8
0%
#205000
1%
#206000
b1011 +
#210000
b1100 =
b1100 !
b1100 <
b1111110101000 7
b110101000 "
b110101000 6
b110010 '
b110010 -
b110010 3
b110010 9
b1001 &
b1001 ,
b1001 2
b1001 8
0%
#215000
1%
#216000
b1100 +
#220000
b0 =
b0 !
b0 <
b0 7
b0 "
b0 6
0(
b0 '
b0 -
b0 3
b0 9
b0 &
b0 ,
b0 2
b0 8
0%
#225000
1%
#230000
b111100111 !
b111100111 <
b1111111100111 =
b110110101 "
b110110101 6
b1111110110101 7
1(
b110011100 '
b110011100 -
b110011100 3
b110011100 9
b11 &
b11 ,
b11 2
b11 8
0%
#235000
1%
#236000
b1101 +
#240000
b1111111110011 =
b111110011 !
b111110011 <
b1111110101000 7
b110101000 "
b110101000 6
b111001110 '
b111001110 -
b111001110 3
b111001110 9
b111 &
b111 ,
b111 2
b111 8
0%
#245000
1%
#246000
b1110 +
#250000
b0 =
b0 !
b0 <
b0 7
b0 "
b0 6
0(
b0 '
b0 -
b0 3
b0 9
b0 &
b0 ,
b0 2
b0 8
0%
#255000
1%
#260000
b111111 !
b111111 <
b111111 =
1(
b11111111 '
b11111111 -
b11111111 3
b11111111 9
0%
#265000
1%
#266000
b1111 +
#270000
b0 =
b0 !
b0 <
0(
b0 '
b0 -
b0 3
b0 9
0%
#275000
1%
#280000
b110010 !
b110010 <
b110010 =
b11111111 "
b11111111 6
b101011110 7
1(
b11001000 '
b11001000 -
b11001000 3
b11001000 9
b111 &
b111 ,
b111 2
b111 8
0%
#285000
1%
#286000
b10000 +
#290000
b1111111000000 =
b111000000 !
b111000000 <
b111111110 7
b11111111 "
b11111111 6
b100000001 '
b100000001 -
b100000001 3
b100000001 9
b1000 &
b1000 ,
b1000 2
b1000 8
0%
#295000
1%
#296000
b10001 +
#300000
b0 =
b0 !
b0 <
b0 7
b0 "
b0 6
0(
b0 '
b0 -
b0 3
b0 9
b0 &
b0 ,
b0 2
b0 8
0%
#305000
1%
#310000
b111111 !
b111111 <
b111111 =
1(
b11111111 '
b11111111 -
b11111111 3
b11111111 9
0%
#315000
1%
#316000
b10010 +
#320000
b0 =
b0 !
b0 <
0(
b0 '
b0 -
b0 3
b0 9
0%
#325000
1%
#330000
b111000000 !
b111000000 <
b1111111000000 =
1(
b100000000 '
b100000000 -
b100000000 3
b100000000 9
0%
#335000
1%
#336000
b10011 +
#340000
b0 =
b0 !
b0 <
0(
b0 '
b0 -
b0 3
b0 9
0%
