src/SNN_core/synapse_core/eligibility_updater.sv
module eligibility_updater #(
    parameter int T_PRE         = 2,
    parameter int T_POST        = 2,
    parameter int TAU_E_SHIFT   = 2,
    parameter int DW_POS        = 16,
    parameter int DW_NEG        = 64,
    parameter int LEARNING_MODE = 1,   // 0: None, 1: R-STDP, 2: STDP
    parameter int MAX_E_TRACE   = 255,
    parameter int MIN_E_TRACE   = -256
  ) (
    input  logic              clk,
    input  logic              pre_spk,
    input  logic              post_spk,
    input  logic              rst,
    output logic signed [8:0] elig_trace
  );

  if (LEARNING_MODE == 0) begin : g_off
    assign elig_trace = '0;
  end else begin : g_on
    localparam int DISABLED = -1;

    // Edge detection
    logic pre_spk_r, post_spk_r;
    logic pre_edge, post_edge;
    assign pre_edge  = pre_spk  & ~pre_spk_r;
    assign post_edge = post_spk & ~post_spk_r;
    logic signed [4:0]  pre_timer, post_timer; // signed to hold DISABLED (-1)
    logic signed [8:0]  e_trace;
    logic signed [10:0] e_next;
    logic signed [10:0] e_comb;

    always_ff @(posedge clk)
    begin
      if (rst) begin
        pre_spk_r  <= 1'b0;
        post_spk_r <= 1'b0;
      end else begin
        pre_spk_r  <= pre_spk;
        post_spk_r <= post_spk;
      end
    end

    // Timer logic (merged)
    always_ff @(posedge clk)
    begin : timer_block
      if (rst) begin
        pre_timer  <= DISABLED;
        post_timer <= DISABLED;
      end else begin
        // Pre timer
        if      (pre_edge)
          pre_timer  <= 0;
        else if (pre_timer  > T_PRE)
          pre_timer  <= DISABLED;
        else if (pre_timer  >= 0)
          pre_timer  <= pre_timer  + 1;

        // Post timer
        if      (post_edge)
          post_timer <= 0;
        else if (post_timer > T_POST)
          post_timer <= DISABLED;
        else if (post_timer >= 0)
          post_timer <= post_timer + 1;
      end
    end

    // Compute next eligibility trace combinationally
    always_comb
    begin : e_next_calc
      e_comb = e_trace;
      if (pre_edge  && post_timer >= 0)
        e_comb = e_comb - DW_NEG; // LTD
      if (post_edge && pre_timer  >= 0)
        e_comb = e_comb + DW_POS; // LTP
      e_comb = e_comb - (e_comb >>> TAU_E_SHIFT); // Decay after STDP updates

      e_next = e_comb;
    end

    // Clamp and register
    always_ff @(posedge clk)
    begin : eligibility_update
      if (rst) begin
        e_trace <= '0;
      end else if (e_next > MAX_E_TRACE) begin
        e_trace <= MAX_E_TRACE;
      end else if (e_next < MIN_E_TRACE) begin
        e_trace <= MIN_E_TRACE;
      end else begin
        e_trace <= e_next[8:0];
      end
    end

    assign elig_trace = e_trace;
  end

endmodule

src/SNN_core/synapse_core/tb_eligibility_updater.sv
`timescale 1ns / 1ps
//////////////////////////////////////////////////////////////////////////////////
// Company:
// Engineer:
//
// Create Date: 04/13/2026
// Design Name:
// Module Name: tb_eligibility_updater
// Project Name:
// Target Devices:
// Tool Versions:
// Description: Testbench for eligibility_updater -- covers learning-mode
//              disable, LTP/LTD updates, timer windows, decay, and clamping.
//
// Dependencies: eligibility_updater.sv
//
// Revision:
// Revision 0.01 - File Created
// Additional Comments:
//
//////////////////////////////////////////////////////////////////////////////////

module tb_eligibility_updater ();

    // --------------------------------------------------------------------------
    // Parameters matching dut_on / dut_off defaults
    // --------------------------------------------------------------------------
    localparam int T_PRE       = 2;
    localparam int T_POST      = 2;
    localparam int TAU_E_SHIFT = 2;
    localparam int DW_POS      = 16;
    localparam int DW_NEG      = 64;
    localparam int MAX_E_TRACE = 255;
    localparam int MIN_E_TRACE = -256;

    // --------------------------------------------------------------------------
    // Shared DUT signals
    // --------------------------------------------------------------------------
    logic clk;
    logic rst;
    logic pre_spk;
    logic post_spk;

    // Output per instance
    logic signed [8:0] elig_off;    // LEARNING_MODE = 0  (always zero)
    logic signed [8:0] elig_on;     // LEARNING_MODE = 1  (default params)
    logic signed [8:0] elig_clamp;  // LEARNING_MODE = 1  (large DW for clamp tests)

    // --------------------------------------------------------------------------
    // DUT instantiation -- one per configuration
    // --------------------------------------------------------------------------
    eligibility_updater #(
        .LEARNING_MODE(0)
    ) dut_off (
        .clk       (clk),
        .pre_spk   (pre_spk),
        .post_spk  (post_spk),
        .rst       (rst),
        .elig_trace(elig_off)
    );

    eligibility_updater #(
        .T_PRE      (T_PRE),
        .T_POST     (T_POST),
        .TAU_E_SHIFT(TAU_E_SHIFT),
        .DW_POS     (DW_POS),
        .DW_NEG     (DW_NEG),
        .LEARNING_MODE(1),
        .MAX_E_TRACE(MAX_E_TRACE),
        .MIN_E_TRACE(MIN_E_TRACE)
    ) dut_on (
        .clk       (clk),
        .pre_spk   (pre_spk),
        .post_spk  (post_spk),
        .rst       (rst),
        .elig_trace(elig_on)
    );

    // Large DW_POS / DW_NEG so a single spike pair saturates the clamp
    eligibility_updater #(
        .DW_POS      (500),
        .DW_NEG      (500),
        .LEARNING_MODE(1)
    ) dut_clamp (
        .clk       (clk),
        .pre_spk   (pre_spk),
        .post_spk  (post_spk),
        .rst       (rst),
        .elig_trace(elig_clamp)
    );

    // --------------------------------------------------------------------------
    // Clock generation -- 10 ns period (100 MHz)
    // --------------------------------------------------------------------------
    initial clk = 1'b0;
    always #5 clk = ~clk;

    // --------------------------------------------------------------------------
    // Pass / fail counters
    // --------------------------------------------------------------------------
    int pass_count = 0;
    int fail_count = 0;

    // --------------------------------------------------------------------------
    // Helper task: drive spike inputs for one clock cycle
    // --------------------------------------------------------------------------
    task automatic apply_spikes(input logic pre_val, post_val);
        @(negedge clk);
        pre_spk  = pre_val;
        post_spk = post_val;
        rst      = 1'b0;
        @(posedge clk);
        #1;  // let outputs settle
    endtask

    // --------------------------------------------------------------------------
    // Helper task: idle (no spikes) for N clock cycles
    // --------------------------------------------------------------------------
    task automatic idle_cycles(input int n);
        repeat (n) apply_spikes(1'b0, 1'b0);
    endtask

    // --------------------------------------------------------------------------
    // Helper task: assert reset for two cycles then release
    // --------------------------------------------------------------------------
    task automatic do_rst();
        @(negedge clk);
        rst      = 1'b1;
        pre_spk  = 1'b0;
        post_spk = 1'b0;
        @(posedge clk); #1;
        @(negedge clk); @(posedge clk); #1;
        rst = 1'b0;
    endtask

    // --------------------------------------------------------------------------
    // Assertion helper: check one output value, print PASS / FAIL
    // --------------------------------------------------------------------------
    task automatic check(
        input string             label,
        input logic signed [8:0] got,
        input logic signed [8:0] expected
    );
        if (got === expected) begin
            $display("  PASS  %s : elig_trace = %0d", label, got);
            pass_count++;
        end else begin
            $display("  FAIL  %s : got %0d, expected %0d", label, got, expected);
            fail_count++;
        end
    endtask

    // --------------------------------------------------------------------------
    // Continuous monitor: show all outputs on every posedge
    // --------------------------------------------------------------------------
    always @(posedge clk) begin
        #1;
        $display("[%0t ns]  pre=%b post=%b | off=%0d  on=%0d  clamp=%0d",
                 $time, pre_spk, post_spk, elig_off, elig_on, elig_clamp);
    end

    // --------------------------------------------------------------------------
    // Stimulus
    // --------------------------------------------------------------------------
    initial begin
        // ----- Initialise -----
        rst      = 1'b1;
        pre_spk  = 1'b0;
        post_spk = 1'b0;

        // ==================================================================
        // TEST 0: Reset -- elig_trace must be zero while rst is asserted
        // ==================================================================
        $display("\n[%0t] TEST 0: Reset -- elig_trace must be zero during rst", $time);
        @(negedge clk); @(posedge clk); #1;
        @(negedge clk); @(posedge clk); #1;
        check("off   | rst=1", elig_off,   9'sd0);
        check("on    | rst=1", elig_on,    9'sd0);
        check("clamp | rst=1", elig_clamp, 9'sd0);
        @(negedge clk);
        rst = 1'b0;
        idle_cycles(1);

        // ==================================================================
        // TEST 1: No-learning mode -- elig_trace must always be zero
        //
        // With LEARNING_MODE=0 the combinational path forces e_comb=0, so
        // no spike pattern can change the registered trace.
        // ==================================================================
        $display("\n[%0t] TEST 1: No-learning mode -- elig_trace always zero", $time);
        apply_spikes(1'b1, 1'b0);
        check("off   | pre=1, post=0", elig_off, 9'sd0);
        apply_spikes(1'b0, 1'b1);
        check("off   | LTP attempt (post after pre)", elig_off, 9'sd0);
        apply_spikes(1'b1, 1'b1);
        check("off   | pre=1, post=1 simultaneous", elig_off, 9'sd0);
        idle_cycles(1);

        // ==================================================================
        // TEST 2: LTP -- post fires 1 cycle after pre
        //
        // pre fires  → pre_timer=0,  e_trace unchanged (no post history)
        // post fires → pre_timer=0 ≥ 0 → LTP:
        //   e_comb = 0 + DW_POS(16) − (16 >>> TAU_E_SHIFT(2)) = 16 − 4 = 12
        // ==================================================================
        $display("\n[%0t] TEST 2: LTP -- post fires 1 cycle after pre", $time);
        do_rst();
        apply_spikes(1'b1, 1'b0);               // pre edge; no post history
        check("on    | pre spike alone",         elig_on, 9'sd0);
        apply_spikes(1'b0, 1'b1);               // post edge 1 cycle later
        check("on    | LTP: post 1 cycle after pre", elig_on, 9'sd12);
        idle_cycles(2);

        // ==================================================================
        // TEST 3: LTD -- pre fires 1 cycle after post
        //
        // post fires → post_timer=0, e_trace unchanged (no pre history)
        // pre fires  → post_timer=0 ≥ 0 → LTD:
        //   e_comb = 0 − DW_NEG(64) − (−64 >>> 2) = −64 + 16 = −48
        // ==================================================================
        $display("\n[%0t] TEST 3: LTD -- pre fires 1 cycle after post", $time);
        do_rst();
        apply_spikes(1'b0, 1'b1);               // post edge; no pre history
        check("on    | post spike alone",        elig_on, 9'sd0);
        apply_spikes(1'b1, 1'b0);               // pre edge 1 cycle later
        check("on    | LTD: pre 1 cycle after post", elig_on, -9'sd48);
        idle_cycles(2);

        // ==================================================================
        // TEST 4: Decay -- trace decays exponentially toward zero
        //
        // Each idle cycle applies: e_next = e_comb − (e_comb >>> TAU_E_SHIFT)
        //   12 → 12 − 3 = 9  → 9 − 2 = 7  → 7 − 1 = 6
        // ==================================================================
        $display("\n[%0t] TEST 4: Decay -- trace decays toward zero", $time);
        do_rst();
        apply_spikes(1'b1, 1'b0);  // build trace via LTP (12)
        apply_spikes(1'b0, 1'b1);
        idle_cycles(1);
        check("on    | decay cycle 1: 12 → 9",  elig_on, 9'sd9);
        idle_cycles(1);
        check("on    | decay cycle 2:  9 → 7",  elig_on, 9'sd7);
        idle_cycles(1);
        check("on    | decay cycle 3:  7 → 6",  elig_on, 9'sd6);
        idle_cycles(2);

        // ==================================================================
        // TEST 5: No STDP without prior spike in window
        //
        // post alone (pre_timer = DISABLED) → no LTP
        // After the post timer expires, pre alone (post_timer = DISABLED) → no LTD
        // ==================================================================
        $display("\n[%0t] TEST 5: No STDP without spike history", $time);
        do_rst();
        apply_spikes(1'b0, 1'b1);  // post fires; pre_timer = -1 → no LTP
        check("on    | post alone, no prior pre → no LTP", elig_on, 9'sd0);
        idle_cycles(T_POST + 3);   // wait for post_timer to expire (DISABLED)
        apply_spikes(1'b1, 1'b0);  // pre fires; post_timer = -1 → no LTD
        check("on    | pre alone, no prior post → no LTD", elig_on, 9'sd0);
        idle_cycles(2);

        // ==================================================================
        // TEST 6: LTP window edge -- post fires T_PRE+2 cycles after pre
        //
        // Timer progression: 0 → 1 → 2 → 3 (T_PRE+1); at posedge where
        // post fires pre_timer = T_PRE+1 = 3 ≥ 0 → still inside window.
        //   e_comb = 0 + 16 − 4 = 12
        // ==================================================================
        $display("\n[%0t] TEST 6: LTP at window edge (post %0d cycles after pre)", $time, T_PRE+2);
        do_rst();
        apply_spikes(1'b1, 1'b0);       // pre edge; pre_timer → 0
        idle_cycles(T_PRE + 1);         // pre_timer → 1, 2, 3
        apply_spikes(1'b0, 1'b1);       // post fires; pre_timer = 3 ≥ 0 → LTP
        check("on    | LTP at window edge", elig_on, 9'sd12);
        idle_cycles(2);

        // ==================================================================
        // TEST 7: LTP window miss -- post fires T_PRE+3 cycles after pre
        //
        // After T_PRE+2 idles, pre_timer has cycled through 3 and been set to
        // DISABLED (−1); post edge sees pre_timer < 0 → no LTP.
        // ==================================================================
        $display("\n[%0t] TEST 7: LTP window miss (post %0d cycles after pre)", $time, T_PRE+3);
        do_rst();
        apply_spikes(1'b1, 1'b0);       // pre edge; pre_timer → 0
        idle_cycles(T_PRE + 2);         // pre_timer → 1, 2, 3, DISABLED
        apply_spikes(1'b0, 1'b1);       // post fires; pre_timer = -1 < 0 → no LTP
        check("on    | LTP window miss → no STDP", elig_on, 9'sd0);
        idle_cycles(2);

        // ==================================================================
        // TEST 8: LTD window edge -- pre fires T_POST+2 cycles after post
        //
        // Symmetric to TEST 6 using post_timer.
        //   e_comb = 0 − 64 − (−64 >>> 2) = −64 + 16 = −48
        // ==================================================================
        $display("\n[%0t] TEST 8: LTD at window edge (pre %0d cycles after post)", $time, T_POST+2);
        do_rst();
        apply_spikes(1'b0, 1'b1);       // post edge; post_timer → 0
        idle_cycles(T_POST + 1);        // post_timer → 1, 2, 3
        apply_spikes(1'b1, 1'b0);       // pre fires; post_timer = 3 ≥ 0 → LTD
        check("on    | LTD at window edge", elig_on, -9'sd48);
        idle_cycles(2);

        // ==================================================================
        // TEST 9: LTD window miss -- pre fires T_POST+3 cycles after post
        //
        // Symmetric to TEST 7 using post_timer.
        // ==================================================================
        $display("\n[%0t] TEST 9: LTD window miss (pre %0d cycles after post)", $time, T_POST+3);
        do_rst();
        apply_spikes(1'b0, 1'b1);       // post edge; post_timer → 0
        idle_cycles(T_POST + 2);        // post_timer → 1, 2, 3, DISABLED
        apply_spikes(1'b1, 1'b0);       // pre fires; post_timer = -1 < 0 → no LTD
        check("on    | LTD window miss → no STDP", elig_on, 9'sd0);
        idle_cycles(2);

        // ==================================================================
        // TEST 10: MAX clamp -- single LTP saturates elig_trace at MAX_E_TRACE
        //
        // dut_clamp: DW_POS=500
        //   e_comb = 0 + 500 − (500 >>> 2) = 375 > MAX_E_TRACE(255) → 255
        // ==================================================================
        $display("\n[%0t] TEST 10: MAX clamp -- LTP with DW_POS=500", $time);
        do_rst();
        apply_spikes(1'b1, 1'b0);  // pre fires
        apply_spikes(1'b0, 1'b1);  // post fires → LTP on dut_clamp (375 > 255)
        check("clamp | LTP clamped to MAX_E_TRACE (255)", elig_clamp, 9'sd255);
        idle_cycles(2);

        // ==================================================================
        // TEST 11: MIN clamp -- single LTD saturates elig_trace at MIN_E_TRACE
        //
        // dut_clamp: DW_NEG=500
        //   e_comb = 0 − 500 − (−500 >>> 2) = −375 < MIN_E_TRACE(−256) → −256
        // ==================================================================
        $display("\n[%0t] TEST 11: MIN clamp -- LTD with DW_NEG=500", $time);
        do_rst();
        apply_spikes(1'b0, 1'b1);  // post fires
        apply_spikes(1'b1, 1'b0);  // pre fires → LTD on dut_clamp (−375 < −256)
        check("clamp | LTD clamped to MIN_E_TRACE (-256)", elig_clamp, 9'sh100);
        idle_cycles(2);

        // ==================================================================
        // Summary
        // ==================================================================
        $display("\n[%0t] ===== Testbench complete: %0d passed, %0d failed =====",
                 $time, pass_count, fail_count);

        if (fail_count == 0)
            $display("[%0t] ALL TESTS PASSED", $time);
        else
            $display("[%0t] %0d TEST(S) FAILED -- see FAIL lines above", $time, fail_count);

        $finish;
    end

    // --------------------------------------------------------------------------
    // Waveform dump (uncomment for iVerilog / non-Vivado flows)
    // --------------------------------------------------------------------------
    initial begin
        $dumpfile("tb_eligibility_updater.vcd");
        $dumpvars(0, tb_eligibility_updater);
    end

endmodule

src/SNN_core/synapse_core/tb_eligibility_updater.vcd
$date
	Mon Apr 13 17:05:16 2026
$end
$version
	Icarus Verilog
$end
$timescale
	1ps
$end
$scope module tb_eligibility_updater $end
$var wire 9 ! elig_on [8:0] $end
$var wire 9 " elig_off [8:0] $end
$var wire 9 # elig_clamp [8:0] $end
$var parameter 32 $ DW_NEG $end
$var parameter 32 % DW_POS $end
$var parameter 32 & MAX_E_TRACE $end
$var parameter 32 ' MIN_E_TRACE $end
$var parameter 32 ( TAU_E_SHIFT $end
$var parameter 32 ) T_POST $end
$var parameter 32 * T_PRE $end
$var reg 1 + clk $end
$var reg 1 , post_spk $end
$var reg 1 - pre_spk $end
$var reg 1 . rst $end
$var integer 32 / fail_count [31:0] $end
$var integer 32 0 pass_count [31:0] $end
$scope module dut_clamp $end
$var wire 1 + clk $end
$var wire 9 1 elig_trace [8:0] $end
$var wire 1 2 post_edge $end
$var wire 1 , post_spk $end
$var wire 1 3 pre_edge $end
$var wire 1 - pre_spk $end
$var wire 1 . rst $end
$var parameter 32 4 DISABLED $end
$var parameter 32 5 DW_NEG $end
$var parameter 32 6 DW_POS $end
$var parameter 32 7 LEARNING_MODE $end
$var parameter 32 8 MAX_E_TRACE $end
$var parameter 32 9 MIN_E_TRACE $end
$var parameter 32 : TAU_E_SHIFT $end
$var parameter 32 ; T_POST $end
$var parameter 32 < T_PRE $end
$var reg 11 = e_comb [10:0] $end
$var reg 11 > e_next [10:0] $end
$var reg 9 ? e_trace [8:0] $end
$var reg 1 @ post_spk_r $end
$var reg 5 A post_timer [4:0] $end
$var reg 1 B pre_spk_r $end
$var reg 5 C pre_timer [4:0] $end
$scope begin e_next_calc $end
$upscope $end
$scope begin eligibility_update $end
$upscope $end
$scope begin timer_block $end
$upscope $end
$upscope $end
$scope module dut_off $end
$var wire 1 + clk $end
$var wire 9 D elig_trace [8:0] $end
$var wire 1 E post_edge $end
$var wire 1 , post_spk $end
$var wire 1 F pre_edge $end
$var wire 1 - pre_spk $end
$var wire 1 . rst $end
$var parameter 32 G DISABLED $end
$var parameter 32 H DW_NEG $end
$var parameter 32 I DW_POS $end
$var parameter 32 J LEARNING_MODE $end
$var parameter 32 K MAX_E_TRACE $end
$var parameter 32 L MIN_E_TRACE $end
$var parameter 32 M TAU_E_SHIFT $end
$var parameter 32 N T_POST $end
$var parameter 32 O T_PRE $end
$var reg 11 P e_comb [10:0] $end
$var reg 11 Q e_next [10:0] $end
$var reg 9 R e_trace [8:0] $end
$var reg 1 S post_spk_r $end
$var reg 5 T post_timer [4:0] $end
$var reg 1 U pre_spk_r $end
$var reg 5 V pre_timer [4:0] $end
$scope begin e_next_calc $end
$upscope $end
$scope begin eligibility_update $end
$upscope $end
$scope begin timer_block $end
$upscope $end
$upscope $end
$scope module dut_on $end
$var wire 1 + clk $end
$var wire 9 W elig_trace [8:0] $end
$var wire 1 X post_edge $end
$var wire 1 , post_spk $end
$var wire 1 Y pre_edge $end
$var wire 1 - pre_spk $end
$var wire 1 . rst $end
$var parameter 32 Z DISABLED $end
$var parameter 32 [ DW_NEG $end
$var parameter 32 \ DW_POS $end
$var parameter 32 ] LEARNING_MODE $end
$var parameter 32 ^ MAX_E_TRACE $end
$var parameter 32 _ MIN_E_TRACE $end
$var parameter 32 ` TAU_E_SHIFT $end
$var parameter 32 a T_POST $end
$var parameter 32 b T_PRE $end
$var reg 11 c e_comb [10:0] $end
$var reg 11 d e_next [10:0] $end
$var reg 9 e e_trace [8:0] $end
$var reg 1 f post_spk_r $end
$var reg 5 g post_timer [4:0] $end
$var reg 1 h pre_spk_r $end
$var reg 5 i pre_timer [4:0] $end
$scope begin e_next_calc $end
$upscope $end
$scope begin eligibility_update $end
$upscope $end
$scope begin timer_block $end
$upscope $end
$upscope $end
$scope task apply_spikes $end
$upscope $end
$scope task check $end
$upscope $end
$scope task do_rst $end
$upscope $end
$scope task idle_cycles $end
$upscope $end
$upscope $end
$enddefinitions $end
$comment Show the parameter values. $end
$dumpall
b10 b
b10 a
b10 `
b11111111111111111111111100000000 _
b11111111 ^
b1 ]
b10000 \
b1000000 [
b11111111111111111111111111111111 Z
b10 O
b10 N
b10 M
b11111111111111111111111100000000 L
b11111111 K
b0 J
b10000 I
b1000000 H
b11111111111111111111111111111111 G
b10 <
b10 ;
b10 :
b11111111111111111111111100000000 9
b11111111 8
b1 7
b111110100 6
b111110100 5
b11111111111111111111111111111111 4
b10 *
b10 )
b10 (
b11111111111111111111111100000000 '
b11111111 &
b10000 %
b1000000 $
$end
#0
$dumpvars
bx i
xh
bx g
xf
bx e
bx d
bx c
0Y
0X
bx W
bx V
xU
bx T
xS
bx R
b0 Q
b0 P
0F
0E
bx D
bx C
xB
bx A
x@
bx ?
bx >
bx =
03
02
bx 1
b0 0
b0 /
1.
0-
0,
0+
bx #
bx "
bx !
$end
#5000
b0 >
b0 =
b0 d
b0 c
b0 #
b0 1
b0 ?
b11111 A
b11111 C
b0 !
b0 W
b0 e
b11111 g
b11111 i
b0 "
b0 D
b0 R
b11111 T
b11111 V
0S
0U
0f
0h
0@
0B
1+
#10000
0+
#15000
1+
#20000
0+
#25000
1+
#26000
b11 0
#30000
0.
0+
#35000
1+
#40000
0+
#45000
1+
#50000
13
1F
1Y
1-
0+
#55000
03
0Y
0F
b0 C
b0 i
b0 V
1B
1h
1U
1+
#56000
b100 0
#60000
b101110111 >
b101110111 =
b1100 d
b1100 c
12
1E
1X
1,
0-
0+
#65000
0E
0X
02
b11000000 >
b11000000 =
b1001 d
b1001 c
b11111111 #
b11111111 1
b11111111 ?
b0 A
b1 C
b1100 !
b1100 W
b1100 e
b0 g
b1 i
b0 T
b1 V
1S
0U
1f
0h
1@
0B
1+
#66000
b101 0
#70000
b11101001001 >
b11101001001 =
b11111011001 d
b11111011001 c
13
1F
1Y
1-
0+
#75000
03
0Y
0F
b11101110111 >
b11101110111 =
b11111100011 d
b11111100011 c
b101001001 #
b101001001 1
b101001001 ?
b1 A
b0 C
b111011001 !
b111011001 W
b111011001 e
b1 g
b0 i
b1 T
b0 V
1B
1h
1U
1+
#76000
b110 0
#80000
0,
0-
0+
#85000
b11110011010 >
b11110011010 =
b11111101011 d
b11111101011 c
b101110111 #
b101110111 1
b101110111 ?
b10 A
b1 C
b111100011 !
b111100011 W
b111100011 e
b10 g
b1 i
b10 T
b1 V
0S
0U
0f
0h
0@
0B
1+
#90000
1.
0+
#95000
b0 >
b0 =
b0 d
b0 c
b0 #
b0 1
b0 ?
b11111 A
b11111 C
b0 !
b0 W
b0 e
b11111 g
b11111 i
b11111 T
b11111 V
1+
#100000
0+
#105000
1+
#106000
0.
#110000
13
1F
1Y
1-
0+
#115000
03
0Y
0F
b0 C
b0 i
b0 V
1B
1h
1U
1+
#116000
b111 0
#120000
b101110111 >
b101110111 =
b1100 d
b1100 c
12
1E
1X
1,
0-
0+
#125000
0E
0X
02
b11000000 >
b11000000 =
b1001 d
b1001 c
b11111111 #
b11111111 1
b11111111 ?
b0 A
b1 C
b1100 !
b1100 W
b1100 e
b0 g
b1 i
b0 T
b1 V
1S
0U
1f
0h
1@
0B
1+
#126000
b1000 0
#130000
0,
0+
#135000
b10010000 >
b10010000 =
b111 d
b111 c
b11000000 #
b11000000 1
b11000000 ?
b1 A
b10 C
b1001 !
b1001 W
b1001 e
b1 g
b10 i
b1 T
b10 V
0@
0f
0S
1+
#140000
0+
#145000
b1101100 >
b1101100 =
b110 d
b110 c
b10010000 #
b10010000 1
b10010000 ?
b10 A
b11 C
b111 !
b111 W
b111 e
b10 g
b11 i
b10 T
b11 V
1+
#150000
1.
0+
#155000
b0 >
b0 =
b0 d
b0 c
b0 #
b0 1
b0 ?
b11111 A
b11111 C
b0 !
b0 W
b0 e
b11111 g
b11111 i
b11111 T
b11111 V
1+
#160000
0+
#165000
1+
#166000
0.
#170000
12
1E
1X
1,
0+
#175000
02
0X
0E
b0 A
b0 g
b0 T
1@
1f
1S
1+
#176000
b1001 0
#180000
b11010001001 >
b11010001001 =
b11111010000 d
b11111010000 c
13
1F
1Y
0,
1-
0+
#185000
0F
0Y
03
b11101000000 >
b11101000000 =
b11111011100 d
b11111011100 c
b100000000 #
b100000000 1
b100000000 ?
b1 A
b0 C
b111010000 !
b111010000 W
b111010000 e
b1 g
b0 i
b1 T
b0 V
0S
1U
0f
1h
0@
1B
1+
#186000
b1010 0
#190000
0-
0+
#195000
b11101110000 >
b11101110000 =
b11111100101 d
b11111100101 c
b101000000 #
b101000000 1
b101000000 ?
b10 A
b1 C
b111011100 !
b111011100 W
b111011100 e
b10 g
b1 i
b10 T
b1 V
0B
0h
0U
1+
#200000
0+
#205000
b11110010100 >
b11110010100 =
b11111101100 d
b11111101100 c
b101110000 #
b101110000 1
b101110000 ?
b11 A
b10 C
b111100101 !
b111100101 W
b111100101 e
b11 g
b10 i
b11 T
b10 V
1+
#210000
1.
0+
#215000
b0 >
b0 =
b0 d
b0 c
b0 #
b0 1
b0 ?
b11111 A
b11111 C
b0 !
b0 W
b0 e
b11111 g
b11111 i
b11111 T
b11111 V
1+
#220000
0+
#225000
1+
#226000
0.
#230000
13
1F
1Y
1-
0+
#235000
03
0Y
0F
b0 C
b0 i
b0 V
1B
1h
1U
1+
#240000
b101110111 >
b101110111 =
b1100 d
b1100 c
12
1E
1X
1,
0-
0+
#245000
0E
0X
02
b11000000 >
b11000000 =
b1001 d
b1001 c
b11111111 #
b11111111 1
b11111111 ?
b0 A
b1 C
b1100 !
b1100 W
b1100 e
b0 g
b1 i
b0 T
b1 V
1S
0U
1f
0h
1@
0B
1+
#250000
0,
0+
#255000
b10010000 >
b10010000 =
b111 d
b111 c
b11000000 #
b11000000 1
b11000000 ?
b1 A
b10 C
b1001 !
b1001 W
b1001 e
b1 g
b10 i
b1 T
b10 V
0@
0f
0S
1+
#256000
b1011 0
#260000
0+
#265000
b1101100 >
b1101100 =
b110 d
b110 c
b10010000 #
b10010000 1
b10010000 ?
b10 A
b11 C
b111 !
b111 W
b111 e
b10 g
b11 i
b10 T
b11 V
1+
#266000
b1100 0
#270000
0+
#275000
b1010001 >
b1010001 =
b101 d
b101 c
b1101100 #
b1101100 1
b1101100 ?
b11 A
b11111 C
b110 !
b110 W
b110 e
b11 g
b11111 i
b11 T
b11111 V
1+
#276000
b1101 0
#280000
0+
#285000
b111101 >
b111101 =
b100 d
b100 c
b1010001 #
b1010001 1
b1010001 ?
b11111 A
b101 !
b101 W
b101 e
b11111 g
b11111 T
1+
#290000
0+
#295000
b101110 >
b101110 =
b11 d
b11 c
b111101 #
b111101 1
b111101 ?
b100 !
b100 W
b100 e
1+
#300000
1.
0+
#305000
b0 >
b0 =
b0 d
b0 c
b0 #
b0 1
b0 ?
b0 !
b0 W
b0 e
1+
#310000
0+
#315000
1+
#316000
0.
#320000
12
1E
1X
1,
0+
#325000
0E
0X
02
b0 A
b0 g
b0 T
1S
1f
1@
1+
#326000
b1110 0
#330000
0,
0+
#335000
b1 A
b1 g
b1 T
0@
0f
0S
1+
#340000
0+
#345000
b10 A
b10 g
b10 T
1+
#350000
0+
#355000
b11 A
b11 g
b11 T
1+
#360000
0+
#365000
b11111 A
b11111 g
b11111 T
1+
#370000
0+
#375000
1+
#380000
13
1F
1Y
1-
0+
#385000
0F
0Y
03
b0 C
b0 i
b0 V
1U
1h
1B
1+
#386000
b1111 0
#390000
0-
0+
#395000
b1 C
b1 i
b1 V
0B
0h
0U
1+
#400000
0+
#405000
b10 C
b10 i
b10 V
1+
#410000
1.
0+
#415000
b11111 C
b11111 i
b11111 V
1+
#420000
0+
#425000
1+
#426000
0.
#430000
13
1F
1Y
1-
0+
#435000
03
0Y
0F
b0 C
b0 i
b0 V
1B
1h
1U
1+
#440000
0-
0+
#445000
b1 C
b1 i
b1 V
0U
0h
0B
1+
#450000
0+
#455000
b10 C
b10 i
b10 V
1+
#460000
0+
#465000
b11 C
b11 i
b11 V
1+
#470000
b101110111 >
b101110111 =
b1100 d
b1100 c
12
1E
1X
1,
0+
#475000
02
0X
0E
b11000000 >
b11000000 =
b1001 d
b1001 c
b11111111 #
b11111111 1
b11111111 ?
b0 A
b11111 C
b1100 !
b1100 W
b1100 e
b0 g
b11111 i
b0 T
b11111 V
1@
1f
1S
1+
#476000
b10000 0
#480000
0,
0+
#485000
b10010000 >
b10010000 =
b111 d
b111 c
b11000000 #
b11000000 1
b11000000 ?
b1 A
b1001 !
b1001 W
b1001 e
b1 g
b1 T
0S
0f
0@
1+
#490000
0+
#495000
b1101100 >
b1101100 =
b110 d
b110 c
b10010000 #
b10010000 1
b10010000 ?
b10 A
b111 !
b111 W
b111 e
b10 g
b10 T
1+
#500000
1.
0+
#505000
b0 >
b0 =
b0 d
b0 c
b0 #
b0 1
b0 ?
b11111 A
b0 !
b0 W
b0 e
b11111 g
b11111 T
1+
#510000
0+
#515000
1+
#516000
0.
#520000
13
1F
1Y
1-
0+
#525000
0F
0Y
03
b0 C
b0 i
b0 V
1U
1h
1B
1+
#530000
0-
0+
#535000
b1 C
b1 i
b1 V
0B
0h
0U
1+
#540000
0+
#545000
b10 C
b10 i
b10 V
1+
#550000
0+
#555000
b11 C
b11 i
b11 V
1+
#560000
0+
#565000
b11111 C
b11111 i
b11111 V
1+
#570000
12
1E
1X
1,
0+
#575000
02
0X
0E
b0 A
b0 g
b0 T
1@
1f
1S
1+
#576000
b10001 0
#580000
0,
0+
#585000
b1 A
b1 g
b1 T
0S
0f
0@
1+
#590000
0+
#595000
b10 A
b10 g
b10 T
1+
#600000
1.
0+
#605000
b11111 A
b11111 g
b11111 T
1+
#610000
0+
#615000
1+
#616000
0.
#620000
12
1E
1X
1,
0+
#625000
0E
0X
02
b0 A
b0 g
b0 T
1S
1f
1@
1+
#630000
0,
0+
#635000
b1 A
b1 g
b1 T
0@
0f
0S
1+
#640000
0+
#645000
b10 A
b10 g
b10 T
1+
#650000
0+
#655000
b11 A
b11 g
b11 T
1+
#660000
b11010001001 >
b11010001001 =
b11111010000 d
b11111010000 c
13
1F
1Y
1-
0+
#665000
0F
0Y
03
b11101000000 >
b11101000000 =
b11111011100 d
b11111011100 c
b100000000 #
b100000000 1
b100000000 ?
b11111 A
b0 C
b111010000 !
b111010000 W
b111010000 e
b11111 g
b0 i
b11111 T
b0 V
1U
1h
1B
1+
#666000
b10010 0
#670000
0-
0+
#675000
b11101110000 >
b11101110000 =
b11111100101 d
b11111100101 c
b101000000 #
b101000000 1
b101000000 ?
b1 C
b111011100 !
b111011100 W
b111011100 e
b1 i
b1 V
0B
0h
0U
1+
#680000
0+
