src/SNN_core/LIF_core/LIF_core.sv
module LIF_core #(
    parameter int DECAY     = 256,
    parameter int THRESHOLD = 1024,
    parameter int RESET     = 0
  ) (
    input  logic        clk,
    input  logic        inhibit,        // Lateral inhibition: suppress spike and reset mem
    input  logic [15:0] i_syn,          // Synaptic input current
    output logic        spk,            // Spike output
    output logic [15:0] pre_reset_mem   // Membrane potential before any reset (used for WTA)
  );

  logic [15:0] mem;
  logic [15:0] mem_next;

  always_ff @(posedge clk)
  begin
    mem_next = (mem > DECAY) ? mem - DECAY + i_syn : i_syn;
    pre_reset_mem <= mem_next;

    if (inhibit) begin
      spk <= 0;
      mem <= RESET;
    end else if (mem_next >= THRESHOLD) begin
      spk <= 1;
      mem <= RESET;
    end else begin
      spk <= 0;
      mem <= mem_next;
    end
  end

endmodule

src/SNN_core/LIF_core/tb_LIF_core.sv
`timescale 1ns / 1ps
//////////////////////////////////////////////////////////////////////////////////
// Company:
// Engineer:
//
// Create Date: 04/13/2026
// Design Name:
// Module Name: tb_LIF_core
// Project Name:
// Target Devices:
// Tool Versions:
// Description: Testbench for LIF_core -- covers membrane integration,
//              threshold/spike/reset, decay, and lateral inhibition.
//
// Dependencies: LIF_core.sv
//
// Revision:
// Revision 0.01 - File Created
// Additional Comments:
//
//////////////////////////////////////////////////////////////////////////////////

module tb_LIF_core ();

    // --------------------------------------------------------------------------
    // Parameters
    // --------------------------------------------------------------------------
    localparam int DECAY     = 256;
    localparam int THRESHOLD = 1024;
    localparam int RESET     = 0;

    // --------------------------------------------------------------------------
    // DUT signals
    // --------------------------------------------------------------------------
    logic        clk;
    logic        inhibit;
    logic [15:0] i_syn;
    logic        spk;
    logic [15:0] pre_reset_mem;

    // --------------------------------------------------------------------------
    // DUT instantiation
    // --------------------------------------------------------------------------
    LIF_core #(
        .DECAY    (DECAY),
        .THRESHOLD(THRESHOLD),
        .RESET    (RESET)
    ) dut (
        .clk          (clk),
        .inhibit      (inhibit),
        .i_syn        (i_syn),
        .spk          (spk),
        .pre_reset_mem(pre_reset_mem)
    );

    // --------------------------------------------------------------------------
    // Clock generation -- 10 ns period (100 MHz)
    // --------------------------------------------------------------------------
    initial clk = 1'b0;
    always #5 clk = ~clk;

    // --------------------------------------------------------------------------
    // Helper task: drive one synaptic input + inhibit value for one clock cycle
    // --------------------------------------------------------------------------
    task automatic apply_input(input logic [15:0] syn_val, input logic inh_val);
        @(negedge clk);
        i_syn   = syn_val;
        inhibit = inh_val;
        @(posedge clk);
        #1; // let outputs settle
    endtask

    // --------------------------------------------------------------------------
    // Helper task: idle (zero input, no inhibit) for N cycles
    // --------------------------------------------------------------------------
    task automatic idle_cycles(input int n);
        repeat (n) apply_input(16'd0, 1'b0);
    endtask

    // --------------------------------------------------------------------------
    // Stimulus
    // --------------------------------------------------------------------------
    initial begin
        // ----- Initialise -----
        inhibit = 1'b0;
        i_syn   = 16'd0;

        // Allow DUT to come out of unknown state
        idle_cycles(2);

        // ==================================================================
        // TEST 1: Membrane accumulation -- no spike expected
        // Apply sub-threshold input over several cycles; membrane should
        // accumulate but not cross THRESHOLD.
        // ==================================================================
        $display("[%0t] TEST 1: sub-threshold accumulation", $time);
        repeat (3) apply_input(16'd300, 1'b0);  // 300 each cycle, well below 1024
        idle_cycles(2);

        // ==================================================================
        // TEST 2: Threshold crossing -- spike expected
        // Drive enough current to push membrane >= THRESHOLD in one shot.
        // ==================================================================
        $display("[%0t] TEST 2: threshold crossing / spike", $time);
        apply_input(16'd1024, 1'b0);  // should trigger spk on next posedge
        idle_cycles(2);

        // ==================================================================
        // TEST 3: Decay -- membrane should decay when input is zero
        // ==================================================================
        $display("[%0t] TEST 3: decay", $time);
        apply_input(16'd512, 1'b0);   // charge membrane to 512
        apply_input(16'd0,   1'b0);   // one decay cycle  (512 - 256 = 256)
        apply_input(16'd0,   1'b0);   // another decay    (256 - 256 = 0)
        idle_cycles(2);

        // ==================================================================
        // TEST 4: Lateral inhibition -- spike suppressed, membrane reset
        // ==================================================================
        $display("[%0t] TEST 4: lateral inhibition", $time);
        apply_input(16'd512,  1'b0);  // build up some membrane potential
        apply_input(16'd1024, 1'b1);  // inhibit active -- spk must stay 0
        idle_cycles(2);

        // ==================================================================
        // TEST 5: Repeated spiking -- membrane resets after each spike
        // ==================================================================
        $display("[%0t] TEST 5: repeated spiking", $time);
        repeat (4) apply_input(16'd1100, 1'b0);
        idle_cycles(2);

        // ==================================================================
        // Add more test cases here as needed
        // ==================================================================

        $display("[%0t] Testbench complete.", $time);
        $finish;
    end

    // --------------------------------------------------------------------------
    // Optional: waveform dump (uncomment for iVerilog / non-Vivado flows)
    // --------------------------------------------------------------------------
    initial begin
        $dumpfile("tb_LIF_core.vcd");
        $dumpvars(0, tb_LIF_core);
    end

endmodule

src/SNN_core/LIF_core/tb_LIF_core.vcd
$date
	Mon Apr 13 09:31:04 2026
$end
$version
	Icarus Verilog
$end
$timescale
	1ps
$end
$scope module tb_LIF_core $end
$var wire 1 ! spk $end
$var wire 16 " pre_reset_mem [15:0] $end
$var parameter 32 # DECAY $end
$var parameter 32 $ RESET $end
$var parameter 32 % THRESHOLD $end
$var reg 1 & clk $end
$var reg 16 ' i_syn [15:0] $end
$var reg 1 ( inhibit $end
$scope module dut $end
$var wire 1 & clk $end
$var wire 16 ) i_syn [15:0] $end
$var wire 1 ( inhibit $end
$var parameter 32 * DECAY $end
$var parameter 32 + RESET $end
$var parameter 32 , THRESHOLD $end
$var reg 16 - mem [15:0] $end
$var reg 16 . mem_next [15:0] $end
$var reg 16 / pre_reset_mem [15:0] $end
$var reg 1 ! spk $end
$upscope $end
$scope task apply_input $end
$upscope $end
$scope task idle_cycles $end
$upscope $end
$upscope $end
$enddefinitions $end
$comment Show the parameter values. $end
$dumpall
b10000000000 ,
b0 +
b100000000 *
b10000000000 %
b0 $
b100000000 #
$end
#0
$dumpvars
bx /
bx .
bx -
b0 )
0(
b0 '
0&
bx "
x!
$end
#5000
0!
1&
#10000
0&
#15000
1&
#20000
0&
#25000
1&
#30000
b100101100 '
b100101100 )
0&
#35000
1&
#40000
0&
#45000
1&
#50000
0&
#55000
1&
#60000
b0 '
b0 )
0&
#65000
1&
#70000
0&
#75000
1&
#80000
b10000000000 '
b10000000000 )
0&
#85000
1&
#90000
b0 '
b0 )
0&
#95000
1&
#100000
0&
#105000
1&
#110000
b1000000000 '
b1000000000 )
0&
#115000
1&
#120000
b0 '
b0 )
0&
#125000
1&
#130000
0&
#135000
1&
#140000
0&
#145000
1&
#150000
0&
#155000
1&
#160000
b1000000000 '
b1000000000 )
0&
#165000
1&
#170000
1(
b10000000000 '
b10000000000 )
0&
#175000
b0 -
1&
#180000
0(
b0 '
b0 )
0&
#185000
b0 "
b0 /
b0 .
1&
#190000
0&
#195000
1&
#200000
b10001001100 '
b10001001100 )
0&
#205000
1!
b10001001100 "
b10001001100 /
b10001001100 .
1&
#210000
0&
#215000
1&
#220000
0&
#225000
1&
#230000
0&
#235000
1&
#240000
b0 '
b0 )
0&
#245000
0!
b0 "
b0 /
b0 .
1&
