src/SNN_core/LIF_core/LIF_core.sv
module LIF_core #(
    parameter int signed DECAY     = 256,
    parameter int signed THRESHOLD = 1024,
    parameter int signed RESET     = 0
  ) (
    input  logic               clk,
    input  logic               inhibit,        // Lateral inhibition: suppress spike and reset mem
    input  logic signed [15:0] i_syn,          // Synaptic input current
    input  logic               rst,            // Reset (active high)
    output logic               spk,            // Spike output
    output logic signed [15:0] pre_reset_mem   // Membrane potential before any reset (used for WTA)
  );

  logic signed [15:0] mem;
  logic signed [15:0] mem_next;

  always_comb begin
    mem_next = (mem > DECAY) ? mem - DECAY + i_syn : i_syn;
  end

  always_ff @(posedge clk)
  begin
    if (rst) begin
      spk           <= '0;
      mem           <= 16'(RESET);
      pre_reset_mem <= 16'(RESET);
    end else begin
      pre_reset_mem <= mem_next;

      if (inhibit) begin
        spk <= '0;
        mem <= 16'(RESET);
      end else if (mem_next >= THRESHOLD) begin
        spk <= '1;
        mem <= 16'(RESET);
      end else begin
        spk <= '0;
        mem <= mem_next;
      end
    end
  end

endmodule

src/SNN_core/LIF_core/tb_LIF_core.sv
`timescale 1ns / 1ps
//////////////////////////////////////////////////////////////////////////////////
// Company:
// Engineer:
//
// Create Date: 04/13/2026
// Design Name:
// Module Name: tb_LIF_core
// Project Name:
// Target Devices:
// Tool Versions:
// Description: Testbench for LIF_core -- covers membrane integration,
//              threshold/spike/reset, decay, and lateral inhibition.
//
// Dependencies: LIF_core.sv
//
// Revision:
// Revision 0.01 - File Created
// Additional Comments:
//
//////////////////////////////////////////////////////////////////////////////////

module tb_LIF_core ();

    // --------------------------------------------------------------------------
    // Parameters
    // --------------------------------------------------------------------------
    localparam int DECAY     = 64;
    localparam int THRESHOLD = 1024;
    localparam int RESET     = 0;

    // --------------------------------------------------------------------------
    // DUT signals
    // --------------------------------------------------------------------------
    logic        clk;
    logic        rst;
    logic        inhibit;
    logic [15:0] i_syn;
    logic        spk;
    logic [15:0] pre_reset_mem;

    // --------------------------------------------------------------------------
    // DUT instantiation
    // --------------------------------------------------------------------------
    LIF_core #(
        .DECAY    (DECAY),
        .THRESHOLD(THRESHOLD),
        .RESET    (RESET)
    ) dut (
        .clk          (clk),
        .rst          (rst),
        .inhibit      (inhibit),
        .i_syn        (i_syn),
        .spk          (spk),
        .pre_reset_mem(pre_reset_mem)
    );

    // --------------------------------------------------------------------------
    // Clock generation -- 10 ns period (100 MHz)
    // --------------------------------------------------------------------------
    initial clk = 1'b0;
    always #5 clk = ~clk;

    // --------------------------------------------------------------------------
    // Helper task: drive one synaptic input + inhibit value for one clock cycle
    // --------------------------------------------------------------------------
    task automatic apply_input(input logic [15:0] syn_val, input logic inh_val);
        @(negedge clk);
        i_syn   = syn_val;
        inhibit = inh_val;
        rst     = 1'b0;
        @(posedge clk);
        #1; // let outputs settle
    endtask

    // --------------------------------------------------------------------------
    // Helper task: idle (zero input, no inhibit) for N cycles
    // --------------------------------------------------------------------------
    task automatic idle_cycles(input int n);
        repeat (n) apply_input(16'd0, 1'b0);
    endtask

    // --------------------------------------------------------------------------
    // Continuous monitor: print membrane and spike on every posedge
    // --------------------------------------------------------------------------
    always @(posedge clk) begin
        #1;
        $display("[%0t ns] i_syn=%0d  pre_reset_mem=%0d  spk=%b",
                 $time, i_syn, pre_reset_mem, spk);
    end

    // --------------------------------------------------------------------------
    // Stimulus
    // --------------------------------------------------------------------------
    initial begin
        // ----- Initialise -----
        rst     = 1'b1;
        inhibit = 1'b0;
        i_syn   = 16'd0;

        // ------------------------------------------------------------------
        // INIT: Hold rst high for 2 cycles to bring mem/spk/pre_reset_mem
        // to RESET (0) before any test begins.
        // ------------------------------------------------------------------
        $display("[%0t] INIT: asserting rst", $time);
        @(negedge clk); @(posedge clk); #1;
        @(negedge clk); @(posedge clk); #1;
        rst = 1'b0;

        // ==================================================================
        // TEST 1: Gradual accumulation to spike
        // Drive i_syn = 150 every cycle.  With DECAY = 64 the net gain is
        // 86 LSB/cycle (once mem > 64), so it takes ~12 cycles to cross
        // THRESHOLD = 1024 and produce a spike.
        //
        // Expected mem trajectory (approximate):
        //   0 -> 150 -> 236 -> 322 -> 408 -> 494 -> 580 -> 666
        //     -> 752 -> 838 -> 924 -> 1010 -> SPIKE (1096 >= 1024)
        // ==================================================================
        $display("[%0t] TEST 1: gradual accumulation -- spike expected ~cycle 12", $time);
        repeat (15) apply_input(16'd150, 1'b0);
        idle_cycles(3);

        // ==================================================================
        // TEST 2: Membrane accumulation -- no spike expected
        // Apply sub-threshold input over several cycles; membrane should
        // accumulate but not cross THRESHOLD.
        // ==================================================================
        $display("[%0t] TEST 2: sub-threshold accumulation", $time);
        repeat (5) apply_input(16'd256, 1'b0);  // net gain 192/cycle
        idle_cycles(3);

        // ==================================================================
        // TEST 3: Single-shot threshold crossing -- spike expected
        // Drive enough current to push membrane >= THRESHOLD in one shot.
        // ==================================================================
        $display("[%0t] TEST 3: single-shot threshold crossing / spike", $time);
        apply_input(16'd1024, 1'b0);
        idle_cycles(3);

        // ==================================================================
        // TEST 4: Decay -- membrane should decay when input is zero
        // ==================================================================
        $display("[%0t] TEST 4: decay", $time);
        apply_input(16'd400, 1'b0);   // charge membrane
        repeat (8) apply_input(16'd0, 1'b0);   // watch it decay by 64/cycle
        idle_cycles(2);

        // ==================================================================
        // TEST 5: Lateral inhibition -- spike suppressed, membrane reset
        // ==================================================================
        $display("[%0t] TEST 5: lateral inhibition", $time);
        apply_input(16'd512,  1'b0);  // build up some membrane potential
        apply_input(16'd1024, 1'b1);  // inhibit active -- spk must stay 0
        idle_cycles(3);

        // ==================================================================
        // TEST 6: Repeated spiking -- membrane resets after each spike
        // ==================================================================
        $display("[%0t] TEST 6: repeated spiking", $time);
        repeat (6) apply_input(16'd1100, 1'b0);
        idle_cycles(3);

        // ==================================================================
        // Add more test cases here as needed
        // ==================================================================

        $display("[%0t] Testbench complete.", $time);
        $finish;
    end

    // --------------------------------------------------------------------------
    // Optional: waveform dump (uncomment for iVerilog / non-Vivado flows)
    // --------------------------------------------------------------------------
    initial begin
        $dumpfile("tb_LIF_core.vcd");
        $dumpvars(0, tb_LIF_core);
    end

endmodule

src/SNN_core/LIF_core/tb_LIF_core.vcd
$date
	Mon Apr 13 12:36:00 2026
$end
$version
	Icarus Verilog
$end
$timescale
	1ps
$end
$scope module tb_LIF_core $end
$var wire 1 ! spk $end
$var wire 16 " pre_reset_mem [15:0] $end
$var parameter 32 # DECAY $end
$var parameter 32 $ RESET $end
$var parameter 32 % THRESHOLD $end
$var reg 1 & clk $end
$var reg 16 ' i_syn [15:0] $end
$var reg 1 ( inhibit $end
$var reg 1 ) rst $end
$scope module dut $end
$var wire 1 & clk $end
$var wire 16 * i_syn [15:0] $end
$var wire 1 ( inhibit $end
$var wire 1 ) rst $end
$var parameter 32 + DECAY $end
$var parameter 32 , RESET $end
$var parameter 32 - THRESHOLD $end
$var reg 16 . mem [15:0] $end
$var reg 16 / mem_next [15:0] $end
$var reg 16 0 pre_reset_mem [15:0] $end
$var reg 1 ! spk $end
$upscope $end
$scope task apply_input $end
$upscope $end
$scope task idle_cycles $end
$upscope $end
$upscope $end
$enddefinitions $end
$comment Show the parameter values. $end
$dumpall
b10000000000 -
b0 ,
b1000000 +
b10000000000 %
b0 $
b1000000 #
$end
#0
$dumpvars
bx 0
bx /
bx .
b0 *
1)
0(
b0 '
0&
bx "
x!
$end
#5000
b0 "
b0 0
b0 .
0!
1&
#10000
0&
#15000
1&
#20000
0&
#25000
1&
#26000
0)
#30000
b10010110 '
b10010110 *
0&
#35000
b10010110 .
b10010110 "
b10010110 0
b10010110 /
1&
#40000
0&
#45000
b11101100 .
b11101100 "
b11101100 0
b11101100 /
1&
#50000
0&
#55000
b101000010 .
b101000010 "
b101000010 0
b101000010 /
1&
#60000
0&
#65000
b110011000 .
b110011000 "
b110011000 0
b110011000 /
1&
#70000
0&
#75000
b111101110 .
b111101110 "
b111101110 0
b111101110 /
1&
#80000
0&
#85000
b1001000100 .
b1001000100 "
b1001000100 0
b1001000100 /
1&
#90000
0&
#95000
b1010011010 .
b1010011010 "
b1010011010 0
b1010011010 /
1&
#100000
0&
#105000
b1011110000 .
b1011110000 "
b1011110000 0
b1011110000 /
1&
#110000
0&
#115000
b1101000110 .
b1101000110 "
b1101000110 0
b1101000110 /
1&
#120000
0&
#125000
b1110011100 .
b1110011100 "
b1110011100 0
b1110011100 /
1&
#130000
0&
#135000
b1111110010 .
b1111110010 "
b1111110010 0
b1111110010 /
1&
#140000
0&
#145000
b0 .
1!
b10001001000 "
b10001001000 0
b10001001000 /
1&
#150000
0&
#155000
b10010110 .
0!
b10010110 "
b10010110 0
b10010110 /
1&
#160000
0&
#165000
b11101100 .
b11101100 "
b11101100 0
b11101100 /
1&
#170000
0&
#175000
b101000010 .
b101000010 "
b101000010 0
b101000010 /
1&
#180000
b0 '
b0 *
0&
#185000
b100000010 .
b100000010 "
b100000010 0
b100000010 /
1&
#190000
0&
#195000
b11000010 .
b11000010 "
b11000010 0
b11000010 /
1&
#200000
0&
#205000
b10000010 .
b10000010 "
b10000010 0
b10000010 /
1&
#210000
b100000000 '
b100000000 *
0&
#215000
b101000010 .
b101000010 "
b101000010 0
b101000010 /
1&
#220000
0&
#225000
b1000000010 .
b1000000010 "
b1000000010 0
b1000000010 /
1&
#230000
0&
#235000
b1011000010 .
b1011000010 "
b1011000010 0
b1011000010 /
1&
#240000
0&
#245000
b1110000010 .
b1110000010 "
b1110000010 0
b1110000010 /
1&
#250000
0&
#255000
b0 .
1!
b10001000010 "
b10001000010 0
b10001000010 /
1&
#260000
b0 '
b0 *
0&
#265000
0!
b0 "
b0 0
b0 /
1&
#270000
0&
#275000
1&
#280000
0&
#285000
1&
#290000
b10000000000 '
b10000000000 *
0&
#295000
1!
b10000000000 "
b10000000000 0
b10000000000 /
1&
#300000
b0 '
b0 *
0&
#305000
0!
b0 "
b0 0
b0 /
1&
#310000
0&
#315000
1&
#320000
0&
#325000
1&
#330000
b110010000 '
b110010000 *
0&
#335000
b110010000 .
b110010000 "
b110010000 0
b110010000 /
1&
#340000
b0 '
b0 *
0&
#345000
b101010000 .
b101010000 "
b101010000 0
b101010000 /
1&
#350000
0&
#355000
b100010000 .
b100010000 "
b100010000 0
b100010000 /
1&
#360000
0&
#365000
b11010000 .
b11010000 "
b11010000 0
b11010000 /
1&
#370000
0&
#375000
b10010000 .
b10010000 "
b10010000 0
b10010000 /
1&
#380000
0&
#385000
b1010000 .
b1010000 "
b1010000 0
b1010000 /
1&
#390000
0&
#395000
b10000 .
b10000 "
b10000 0
b10000 /
1&
#400000
0&
#405000
b0 .
b0 "
b0 0
b0 /
1&
#410000
0&
#415000
1&
#420000
0&
#425000
1&
#430000
0&
#435000
1&
#440000
b1000000000 '
b1000000000 *
0&
#445000
b1000000000 .
b1000000000 "
b1000000000 0
b1000000000 /
1&
#450000
1(
b10000000000 '
b10000000000 *
0&
#455000
b0 .
b10111000000 "
b10111000000 0
b10111000000 /
1&
#460000
0(
b0 '
b0 *
0&
#465000
b0 "
b0 0
b0 /
1&
#470000
0&
#475000
1&
#480000
0&
#485000
1&
#490000
b10001001100 '
b10001001100 *
0&
#495000
1!
b10001001100 "
b10001001100 0
b10001001100 /
1&
#500000
0&
#505000
1&
#510000
0&
#515000
1&
#520000
0&
#525000
1&
#530000
0&
#535000
1&
#540000
0&
#545000
1&
#550000
b0 '
b0 *
0&
#555000
0!
b0 "
b0 0
b0 /
1&
